idspy/__init__.py
idspy/commands/__init__.py
idspy/commands/create_language_sheet.py
idspy-0.3.0.dist-info/LICENSE
idspy-0.3.0.dist-info/METADATA
idspy-0.3.0.dist-info/WHEEL
idspy-0.3.0.dist-info/entry_points.txt
idspy-0.3.0.dist-info/top_level.txt
idspy-0.3.0.dist-info/RECORD
